oaas_sdk_grpc/__init__.py
oaas_sdk_grpc/model.py
oaas_sdk_grpc/gen_grpc/__init__.py
oaas_sdk_grpc/gen_grpc/oprc_invoker_pb2.py
oaas_sdk_grpc/gen_grpc/oprc_invoker_pb2.pyi
oaas_sdk_grpc/gen_grpc/oprc_invoker_pb2_grpc.py
oaas_sdk_grpc/gen_grpc/oprc_object_pb2.py
oaas_sdk_grpc/gen_grpc/oprc_object_pb2.pyi
oaas_sdk_grpc/gen_grpc/oprc_object_pb2_grpc.py
oaas_sdk_grpc/gen_grpc/oprc_offload_pb2.py
oaas_sdk_grpc/gen_grpc/oprc_offload_pb2.pyi
oaas_sdk_grpc/gen_grpc/oprc_offload_pb2_grpc.py
oaas_sdk_grpc-0.0.5.dist-info/METADATA
oaas_sdk_grpc-0.0.5.dist-info/WHEEL
oaas_sdk_grpc-0.0.5.dist-info/top_level.txt
oaas_sdk_grpc-0.0.5.dist-info/RECORD
