Metadata-Version: 2.1
Name: oaas-sdk-grpc
Version: 0.0.5
Summary: GRPC SDK for OAAS
Home-page: https://github.com/woraamy/oaas-oprc-grpc-py
Author: Worawalan Chatlatanagulchai
Author-email: worawalanc@gmail.com
Classifier: Programming Language :: Python :: 3
Classifier: Operating System :: OS Independent
Requires-Python: >=3.6
